<?xml version="1.0" encoding="UTF-8"?>

<mime-info xmlns="http://www.freedesktop.org/standards/shared-mime-info">

	<mime-type type="application/x-krecipes-backup">
		<glob pattern="*.krecbk" />
		<sub-class-of type="application/x-gzip"/>
		<comment>Krecipes Backup file</comment>
		<comment xml:lang="bs">Krecipes rezervna datoteka</comment>
		<comment xml:lang="ca">Fitxer de còpia de seguretat del Krecipes</comment>
		<comment xml:lang="cs">Záložní soubor Krecipes</comment>
		<comment xml:lang="da">Krecipes backup-fil</comment>
		<comment xml:lang="de">Krecipes-Datensicherungsdatei</comment>
		<comment xml:lang="el">Krecipes εφεδρικό αρχείο</comment>
		<comment xml:lang="en_GB">Krecipes Backup file</comment>
		<comment xml:lang="es">Archivo de copia de respaldo de Krecipes</comment>
		<comment xml:lang="fi">Krecipes-varmuuskopiotiedosto</comment>
		<comment xml:lang="nl">KRecipes reservekopiebestand</comment>
		<comment xml:lang="pl">Plik kopii zapasowej KPrzepisy</comment>
		<comment xml:lang="pt">Cópia de Segurança do Krecipes</comment>
		<comment xml:lang="pt_BR">Arquivo de backup do Krecipes</comment>
		<comment xml:lang="ru">файл резервной копии Krecipes</comment>
		<comment xml:lang="sk">Záložný súbor Krecipes</comment>
		<comment xml:lang="sl">Datoteka z varnostno kopijo Krecipes</comment>
		<comment xml:lang="sv">Krecept säkerhetskopieringsfil</comment>
		<comment xml:lang="tr">Krecipes Yedekleme dosyası</comment>
		<comment xml:lang="uk">файл резервної копії Krecipes</comment>
	</mime-type>

	<mime-type type="application/x-krecipes-recipes">
		<glob pattern="*.kreml" />
		<sub-class-of type="text/xml" />
		<comment>Krecipes Exported Recipes</comment>
		<comment xml:lang="bs">Krecipes izvezeni recepti</comment>
		<comment xml:lang="ca">Receptes exportades del Krecipes</comment>
		<comment xml:lang="cs">Exportované recepty Krecipes</comment>
		<comment xml:lang="da">Krecipes eksporterede opskrifter</comment>
		<comment xml:lang="de">Krecipes Exportierte Rezepte</comment>
		<comment xml:lang="el">Krecipes εξαχθείσες συνταγές</comment>
		<comment xml:lang="en_GB">Krecipes Exported Recipes</comment>
		<comment xml:lang="es">Recetas exportadas de Krecipes</comment>
		<comment xml:lang="fi">Viedyt Krecipes-reseptit</comment>
		<comment xml:lang="nl">Geëxporteerde recepten van Krecipes</comment>
		<comment xml:lang="pl">Wyeksportowane przepisy KPrzepisów</comment>
		<comment xml:lang="pt">Receitas Exportadas pelo Krecipes</comment>
		<comment xml:lang="pt_BR">Receitas exportadas do Krecipes</comment>
		<comment xml:lang="ru">экспортированные рецепты Krecipes</comment>
		<comment xml:lang="sk">Exportované recepty Krecipes</comment>
		<comment xml:lang="sl">Izvoženi recepti Krecipes</comment>
		<comment xml:lang="sv">Krecept exporterade recept</comment>
		<comment xml:lang="tr">Krecipes Dışa Aktarılan Tarifleri</comment>
		<comment xml:lang="uk">експортовані рецепти Krecipes</comment>
	</mime-type>

	<mime-type type="application/x-krecipes-recipes-compressed">
		<glob pattern="*.kre" />
		<sub-class-of type="application/x-tarz"/>
		<comment>Krecipes Exported Recipes (compressed data)</comment>
		<comment xml:lang="bs">Krecipes izvezeni recepti (kompresovani podaci)</comment>
		<comment xml:lang="ca">Receptes exportades del Krecipes (dades comprimides)</comment>
		<comment xml:lang="cs">Exportované recepty Krecipes (zkomprimovaná data)</comment>
		<comment xml:lang="da">Krecipes eksporterede opskrifter (komprimerede data)</comment>
		<comment xml:lang="de">Krecipes Exportierte Rezepte (komprimierte Daten)</comment>
		<comment xml:lang="el">Krecipes εξαχθείσες συνταγές (συμπιεσμένα δεδομένα)</comment>
		<comment xml:lang="en_GB">Krecipes Exported Recipes (compressed data)</comment>
		<comment xml:lang="es">Recetas exportadas de Krecipes (datos comprimidos)</comment>
		<comment xml:lang="fi">Viedyt Krecipes-reseptit(pakattuna)</comment>
		<comment xml:lang="nl">Geëxporteerde recepten van Krecipes (gecomprimeerde gegevens)</comment>
		<comment xml:lang="pl">Wyeksportowane przepisy KPrzepisów (spakowane dane)</comment>
		<comment xml:lang="pt">Receitas Exportadas pelo Krecipes (dados comprimidos)</comment>
		<comment xml:lang="pt_BR">Receitas exportadas do Krecipes (dados compactados)</comment>
		<comment xml:lang="ru">экспортированные рецепты Krecipes (сжатые данные)</comment>
		<comment xml:lang="sk">Exportované recepty Krecipes (komprimované dáta)</comment>
		<comment xml:lang="sl">Izvoženi recepti Krecipes (stisnjeni podatki)</comment>
		<comment xml:lang="sv">Krecept exporterade recept (komprimerad data)</comment>
		<comment xml:lang="tr">Krecipes Dışa Aktarılan Tarifleri (sıkıştırılmış veri)</comment>
		<comment xml:lang="uk">експортовані рецепти Krecipes (стиснені дані)</comment>
	</mime-type>

</mime-info>
